cognitron/__init__.py
cognitron/package.py
cognitron/core/__init__.py
cognitron/core/annotation.py
cognitron/core/embedding.py
cognitron/core/geometry.py
cognitron/core/hub.py
cognitron/core/image.py
cognitron/core/marimo.py
cognitron/core/utils.py
cognitron/core/video.py
cognitron/pipeline/__init__.py
cognitron/pipeline/accelerator.py
cognitron/pipeline/device.py
cognitron/pipeline/pipeline.py
cognitron/task/__init__.py
cognitron/task/face_detection/__init__.py
cognitron/task/face_detection/meta.py
cognitron/task/face_detection/options.py
cognitron/task/face_detection/pipeline.py
cognitron/task/face_detection/scrfd.py
cognitron/task/face_detection/transform.py
cognitron/task/face_recognition/__init__.py
cognitron/task/face_recognition/arcface.py
cognitron/task/face_recognition/meta.py
cognitron/task/face_recognition/options.py
cognitron/task/face_recognition/pipeline.py
cognitron-0.0.1.dist-info/METADATA
cognitron-0.0.1.dist-info/WHEEL
cognitron-0.0.1.dist-info/licenses/LICENSE
cognitron-0.0.1.dist-info/RECORD
