Metadata-Version: 2.4
Name: cognitron
Version: 0.0.1
Summary: Easy-to-use model inference for the digital humanities
Project-URL: Homepage, https://example.com
Project-URL: Documentation, https://readthedocs.org
Project-URL: Repository, https://github.com/me/spam.git
Author-email: Bernhard Liebl <liebl@informatik.uni-leipzig.de>
License:  GNU GENERAL PUBLIC LICENSE
License-File: LICENSE
Classifier: Development Status :: 2 - Pre-Alpha
Classifier: Intended Audience :: Education
Classifier: Intended Audience :: Science/Research
Classifier: License :: OSI Approved :: GNU General Public License v3 (GPLv3)
Classifier: Operating System :: OS Independent
Classifier: Programming Language :: Python :: 3
Requires-Python: <3.13,>=3.12
Requires-Dist: colour-science>=0.4.6
Requires-Dist: matplotlib>=3.10
Requires-Dist: networkx>=3.4.2
Requires-Dist: numpy>=2.2.1
Requires-Dist: pillow>=11.1.0
Requires-Dist: pydantic>=2.8.2
Requires-Dist: requests>=2.32.3
Requires-Dist: tqdm>=4.67.1
Provides-Extra: cli
Requires-Dist: click; extra == 'cli'
Requires-Dist: rich; extra == 'cli'
